Workbook

Sheet Current
A1: Address: | B1: 120 Longwater Dr Norwell, MA
A2: Unit Count: | B2: 0
A3: Rentable SF: | B3: 51035
B5: Unit | C5: Income | D5: Tenant | E5: SF | F5: Per SF | G5: Lease Term | H5: CAM/TAX | I5: Pro Forma | J5: Per SF | K5: CAM/TAX | M5: Expenses | N5: Current | O5: Per SF | P5: Pro Forma | Q5: Per SF | R5: Notes | T5: Mortgage Calculator
B6: 101 | C6: 7398.15 | D6: Contravisory | E6: 3515 | F6: =(C6/E6)*12 -> 25.256842 | G6: 46173 | H6: 439.37 | I6: 7322.92 | J6: =(I6/E6)*12 -> 25.000011 | K6: =H6 -> 439.37 | M6: Taxes | N6: =N33 -> 74922.398 | O6: =N6/51035 -> 1.4680591 | P6: =N6 -> 74922.398 | Q6: =P6/51035 -> 1.4680591 | R6: assessed $5,566,300 | T6: Loan Amount | U6: =V6*B25 -> 5950000 | V6: =1-C31 -> 0.7
B7: 102 | C7: 16628.21 | D7: Alera Group | E7: 8491 | F7: =(C7/E7)*12 -> 23.500002 | G7: 47269 | H7: 707.58 | I7: 16274.42 | J7: =(I7/E7)*12 -> 23.000005 | K7: =H7 -> 707.58 | M7: Insurance | N7: 10701 | O7: =N7/51035 -> 0.20967963 | P7: 22000 | Q7: =P7/51035 -> 0.43107671 | R7: estimate | T7: Annual Interest Rate | U7: 0.065
B8: 103 | C8: 13160.42 | D8: Veterans Development Corp | E8: 6317 | F8: =(C8/E8)*12 -> 25.000006 | G8: 46630 | H8: 0 | I8: =C8 -> 13160.42 | J8: =(I8/E8)*12 -> 25.000006 | K8: 0 | M8: Water | N8: 5048 | O8: =N8/51035 -> 0.098912511 | P8: =N8 -> 5048 | Q8: =P8/51035 -> 0.098912511 | T8: Life Loan (in years) | U8: 25
B9: 105 | C9: =(F9*E9)/12 -> 4087.5 | D9: NORD | E9: 1962 | F9: 25 | G9: 47848 | H9: 245.25 | I9: =E9*25/12 -> 4087.5 | J9: =(I9/E9)*12 -> 25 | K9: =E9*0.125 -> 245.25 | M9: Sewer | N9: 4856 | O9: =N9/51035 -> 0.095150387 | P9: =N9 -> 4856 | Q9: =P9/51035 -> 0.095150387 | T9: Number of Payments per year | U9: 12
B10: 106 | C10: 8985.37 | D10: Jets.com | E10: 4401 | F10: =(C10/E10)*12 -> 24.499986 | G10: 47879 | H10: 550.13 | I10: 8802 | J10: =(I10/E10)*12 -> 24 | K10: =H10 -> 550.13 | M10: Electric | N10: 77118 | O10: =N10/51035 -> 1.5110806 | P10: =N10 -> 77118 | Q10: =P10/51035 -> 1.5110806 | T10: Total Number of Payments | U10: =U8*U9 -> 300
B11: 200 | C11: 59077.44 | D11: NVNA Foundation, Inc. | E11: 26349 | F11: =(C11/E11)*12 -> 26.905358 | G11: 46276 | H11: 3160.5 | I11: 59077.44 | J11: =(I11/E11)*12 -> 26.905358 | K11: 3160.5 | M11: Heat | N11: 147867 | O11: =N11/51035 -> 2.8973646 | P11: =N11 -> 147867 | Q11: =P11/51035 -> 2.8973646 | R11: electric | T11: Payment per Period | U11: =-PMT(U7/U9,U10,U6) -> 40174.826
B12: Monthly | C12: =SUM(C6:C11) -> 109337.09 | E12: =SUM(E6:E11) -> 51035 | H12: =SUM(H6:H11) -> 5102.83 | I12: =SUM(I6:I11) -> 108724.7 | K12: =SUM(K6:K11) -> 5102.83 | M12: Repairs & Maintenance | N12: 26000 | O12: =N12/51035 -> 0.5094543 | P12: =N12 -> 26000 | Q12: =P12/51035 -> 0.5094543 | T12: Sum of Payments | U12: =U10*U11 -> 12052448
B13: Annually | C13: =C12*12 -> 1312045.1 | H13: =H12*12 -> 61233.96 | I13: =I12*12 -> 1304696.4 | K13: =K12*12 -> 61233.96 | M13: Snow & Landscape | N13: =36630+18385 -> 55015 | O13: =N13/51035 -> 1.0779857 | P13: 50000 | Q13: =P13/51035 -> 0.9797198 | T13: Interest Cost | U13: =U6-U12 -> -6102447.8
M14: Property Management (5%) | N14: =B18*0.05 -> 62322.141 | O14: =N14/51035 -> 1.2211647 | P14: =I18*0.05 -> 61973.079 | Q14: =P14/51035 -> 1.2143251
M15: Trash Removal | N15: 8953 | O15: =N15/51035 -> 0.17542863 | P15: =N15 -> 8953 | Q15: =P15/51035 -> 0.17542863 | T15: DCR | U15: =B23/(U11*12) -> 1.6167039
A16: GOI | B16: =C13 -> 1312045.1 | I16: =I13 -> 1304696.4 | M16: Fire Alarm | N16: 0 | O16: =N16/51035 -> 0 | P16: =N16 -> 0 | Q16: =P16/51035 -> 0
A17: Vacancy | B17: =B16*C17 -> -65602.254 | C17: -0.05 | I17: =I16*J17 -> -65234.82 | J17: -0.05 | M17: Security / Telephone | N17: =2344.64/0.833 -> 2814.6939 | O17: =N17/51035 -> 0.055152226 | P17: =N17 -> 2814.6939 | Q17: =P17/51035 -> 0.055152226 | R17: communications?
A18: GOI (less vacancy) | B18: =SUM(B16:B17) -> 1246442.8 | I18: =SUM(I16:I17) -> 1239461.6 | M18: Elevator Maintenance | N18: 3630 | O18: =N18/51035 -> 0.071127657 | P18: =N18 -> 3630 | Q18: =P18/51035 -> 0.071127657 | T18: Pro- Forma / Refi Mortgage Calculator
A19: Tenant Reimbursements | B19: =H13 -> 61233.96 | F19: aler | I19: =K13 -> 61233.96 | M19: Payroll | N19: 0 | O19: =N19/51035 -> 0 | P19: =N19 -> 0 | Q19: =P19/51035 -> 0 | T19: Loan Amount | U19: =V19*I25 -> 5950000 | V19: =1-J31 -> 0.7
A20: Gross Effective | B20: =SUM(B18:B19) -> 1307676.8 | I20: =SUM(I18:I19) -> 1300695.5 | M20: Janitorial / Cleaning | N20: 49020 | O20: =N20/51035 -> 0.96051729 | P20: =N20 -> 49020 | Q20: =P20/51035 -> 0.96051729 | T20: Annual Interest Rate | U20: 0.065
D21: Cap Rate | E21: Price | F21: Pro Forma Cap Rate | M21: Total Expenses: | N21: =SUM(N6:N20) -> 528267.23 | O21: =N21/51035 -> 10.351077 | P21: =SUM(P6:P20) -> 534202.17 | Q21: =P21/51035 -> 10.467369 | T21: Life Loan (in years) | U21: 25
A22: Total Expenses: | B22: =N21 -> 528267.23 | D22: 0.075 | E22: =B23/D22 -> 10392127 | F22: =I23/E22 -> 0.073757118 | I22: =P21 -> 534202.17 | T22: Number of Payments per year | U22: 12
A23: NOI | B23: =B20-B22 -> 779409.55 | D23: 0.08 | E23: =B23/D23 -> 9742619.4 | F23: =I23/E23 -> 0.07867426 | I23: =I20-I22 -> 766493.37 | M23: Expense Ratio | N23: =N21/B18 -> 0.42381987 | P23: =P21/I18 -> 0.43099534 | T23: Total Number of Payments | U23: =U21*U22 -> 300
A24: Cap Rate | B24: =B23/B25 -> 0.091695242 | D24: 0.085 | E24: =B23/D24 -> 9169524.2 | F24: =I23/E24 -> 0.083591401 | I24: =I23/I25 -> 0.09017569 | M24: Per SF | N24: =N21/B3 -> 10.351077 | P24: =P21/B3 -> 10.467369 | T24: Payment per Period | U24: =-PMT(U20/U22,U23,U19) -> 40174.826
A25: List Price | B25: 8500000 | D25: 0.09 | E25: =B23/D25 -> 8660106.1 | F25: =I23/E25 -> 0.088508542 | I25: =B25 -> 8500000 | T25: Sum of Payments | U25: =U23*U24 -> 12052448
A26: Per SF | B26: =B25/B3 -> 166.55237 | D26: 0.095 | E26: =B23/D26 -> 8204311.1 | F26: =I23/E26 -> 0.093425683 | I26: =I25/E12 -> 166.55237 | T26: Interest Cost | U26: =U19-U25 -> -6102447.8
D27: 0.1 | E27: =B23/D27 -> 7794095.5 | F27: =I23/E27 -> 0.098342825
A28: Mortgage | B28: =U11*12 -> 482097.91 | I28: =U24*12 -> 482097.91 | T28: DCR | U28: =I23/(U24*12) -> 1.5899122
A29: Cash Flow | B29: =B23-B28 -> 297311.64 | I29: =I23-I28 -> 284395.46
A30: Cash on Cash | B30: =B29/B31 -> 0.1165928 | I30: =I29/I31 -> 0.11152763
A31: $ down | B31: =B25*C31 -> 2550000 | C31: 0.3 | I31: =I25*J31 -> 2550000 | J31: 0.3 | N31: 5566300 | P31: =I25*0.7 -> 5950000
N32: =N31/1000 -> 5566.3 | P32: =P31/1000 -> 5950
N33: =N32*13.46 -> 74922.398 | P33: =P32*13.46 -> 80087

Sheet Financial Summary
E3: Current | F3: Pro Forma
B4: Income Summary | C4: Price | E4: =Current!B25 -> 8500000 | F4: =E4 -> 8500000
C5: Price/SF | E5: =E4/51035 -> 166.55237 | F5: =E5 -> 166.55237
C6: GRM | E6: =E4/E11 -> 6.4784359 | F6: =F4/F11 -> 6.5149256
C7: CAP Rate | E7: =E17/E4 -> 0.091695242 | F7: =F17/F4 -> 0.09017569
C8: Cash-on-Cash Return | E8: =E23/E19 -> 0.1165928 | F8: =F23/F19 -> 0.11152763
C9: Debt Coverage Ratio | E9: =E17/E21 -> 1.6167039 | F9: =F17/F21 -> 1.5899122
B11: Operating Data | C11: Gross Scheduled Income | E11: =Current!B16 -> 1312045.1 | F11: =Current!I16 -> 1304696.4
C12: Other Income | E12: =SUM(Current!B19:B19) -> 61233.96 | F12: =SUM(Current!I19:I19) -> 61233.96
C13: Total Scheduled Income | E13: =E11+E12 -> 1373279 | F13: =F11+F12 -> 1365930.4
C14: Vacancy Cost | E14: =-E11*0.05 -> -65602.254 | F14: =-F11*0.05 -> -65234.82
C15: Gross Income | E15: =E13+E14 -> 1307676.8 | F15: =F13+F14 -> 1300695.5
C16: Operating Expenses | E16: =-Current!N21 -> -528267.23 | F16: =-Current!P21 -> -534202.17
C17: Net Operating Income | E17: =E15+E16 -> 779409.55 | F17: =F15+F16 -> 766493.37
B19: Financing Data | C19: Down Payment | E19: =Current!B31 -> 2550000 | F19: =Current!I31 -> 2550000
C20: Loan Amount | E20: =Current!U6 -> 5950000 | F20: =E20 -> 5950000
C21: Debt Service | E21: =Current!B28 -> 482097.91 | F21: =F22*12 -> 482097.91
C22: Debt Service Monthly | E22: =Current!U11 -> 40174.826 | F22: =E22 -> 40174.826
C23: Pre-Tax Cash Flow | E23: =E17-E21 -> 297311.64 | F23: =F17-F21 -> 284395.46
B25: ** Loan information is for illustrative purposes and is subject to change. Please conduct your own independent review
